mcp_echo_streamablehttp_server_stateful/__init__.py
mcp_echo_streamablehttp_server_stateful/__main__.py
mcp_echo_streamablehttp_server_stateful/server.py
mcp_echo_streamablehttp_server_stateful-0.2.0.dist-info/METADATA
mcp_echo_streamablehttp_server_stateful-0.2.0.dist-info/WHEEL
mcp_echo_streamablehttp_server_stateful-0.2.0.dist-info/entry_points.txt
mcp_echo_streamablehttp_server_stateful-0.2.0.dist-info/licenses/LICENSE
mcp_echo_streamablehttp_server_stateful-0.2.0.dist-info/RECORD
