Metadata-Version: 2.4
Name: mcp-echo-streamablehttp-server-stateful
Version: 0.2.0
Summary: A stateful diagnostic MCP echo server with 11 comprehensive tools for debugging OAuth flows, session management, and analyzing software engineering excellence
Project-URL: Homepage, https://github.com/atrawog/mcp-oauth-gateway/tree/main/mcp-echo-streamablehttp-server-stateful
Project-URL: Repository, https://github.com/atrawog/mcp-oauth-gateway/tree/main/mcp-echo-streamablehttp-server-stateful
Project-URL: Issues, https://github.com/atrawog/mcp-oauth-gateway/issues
Project-URL: Documentation, https://atrawog.github.io/mcp-oauth-gateway
Author-email: Andreas Trawoeger <atrawog@gmail.com>
License-Expression: Apache-2.0
License-File: LICENSE
Requires-Python: >=3.10
Requires-Dist: httpx>=0.27.0
Requires-Dist: mcp>=1.3.0
Requires-Dist: psutil>=5.9.0
Requires-Dist: pydantic>=2.0.0
Requires-Dist: python-dotenv>=1.0.0
Requires-Dist: uvicorn>=0.30.0
